{
    "header": {
        "metadata": [
            {
                "metaName": "adskGraphlibVersion",
                "metaType": "string",
                "metaValue": "1.0"
            },
            {
                "metaName": "adskFileFormatVersion",
                "metaValue": "100L"
            }
        ]
    },
    "dependencies": [
        {
            "uri": "file:///getDt.json"
        },
        {
            "uri": "file:///basenodes.json"
        },
        {
            "uri": "file:///getDt.json"
        },
        {
            "uri": "file:///basenodes.json"
        }
    ],
    "types": [],
    "operators": [],
    "compounds": [
        {
            "name": "Bifrost::_private::applyForces",
            "ports": [
                {
                    "portName": "object",
                    "portDirection": "input",
                    "portType": "Bifrost::Types::Object"
                },
                {
                    "portName": "value",
                    "portDirection": "output",
                    "portType": "Bifrost::Types::Object"
                },
                {
                    "portName": "gravityVector",
                    "portDirection": "input",
                    "portType": "Bifrost::Types::Vec3Float"
                },
                {
                    "portName": "gravityMagnitude",
                    "portDirection": "input",
                    "portType": "float"
                },
                {
                    "portName": "forceObject",
                    "portDirection": "input",
                    "portType": "Bifrost::Types::Object"
                },
                {
                    "portName": "isAdaptive",
                    "portDirection": "input",
                    "portType": "bool"
                },
                {
                    "portName": "dropletThreshold",
                    "portDirection": "input",
                    "portType": "float"
                }
            ],
            "compounds": [
                {
                    "name": "applyForcesInternal",
                    "ports": [
                        {
                            "portName": "object",
                            "portDirection": "input",
                            "portType": "Bifrost::Types::Object"
                        },
                        {
                            "portName": "velocity",
                            "portDirection": "input",
                            "portType": "Bifrost::Types::VoxelChannelVelocity"
                        },
                        {
                            "portName": "position",
                            "portDirection": "input",
                            "portType": "Bifrost::Types::PointChannelVec3Float"
                        },
                        {
                            "portName": "dt",
                            "portDirection": "input",
                            "portType": "float"
                        },
                        {
                            "portName": "outVelocity",
                            "portDirection": "output",
                            "portType": "Bifrost::Types::VoxelChannelVelocity"
                        }
                    ],
                    "compoundNodes": [
                        {
                            "nodeName": "ForceVoxelComponent",
                            "nodeType": "Bifrost::Nodes::Component::getVoxelComponent"
                        },
                        {
                            "nodeName": "applyAccelerationForces",
                            "nodeType": "Bifrost::Nodes::Channel::applyAccelerationForces"
                        },
                        {
                            "nodeName": "boundaryLayerBandwidth",
                            "nodeType": "Bifrost::Nodes::Misc::valueString"
                        },
                        {
                            "nodeName": "boundaryLayerBandwidthChannel",
                            "nodeType": "Bifrost::Nodes::Channel::getChannel"
                        },
                        {
                            "nodeName": "boundaryLayerStrength",
                            "nodeType": "Bifrost::Nodes::Misc::valueString"
                        },
                        {
                            "nodeName": "boundaryLayerStrengthChannel",
                            "nodeType": "Bifrost::Nodes::Channel::getChannel"
                        },
                        {
                            "nodeName": "direction",
                            "nodeType": "Bifrost::Nodes::Misc::valueString"
                        },
                        {
                            "nodeName": "directionChannel",
                            "nodeType": "Bifrost::Nodes::Channel::getChannel"
                        },
                        {
                            "nodeName": "fallOffBandwidthChannel",
                            "nodeType": "Bifrost::Nodes::Channel::getChannel"
                        },
                        {
                            "nodeName": "falloffBandwidth",
                            "nodeType": "Bifrost::Nodes::Misc::valueString"
                        },
                        {
                            "nodeName": "forceVoxelComponentName",
                            "nodeType": "Bifrost::Nodes::_privNames::getVoxelComponentName"
                        },
                        {
                            "nodeName": "forceVoxelVelocityChannel",
                            "nodeType": "Bifrost::Nodes::Channel::getVoxelChannelVelocity"
                        },
                        {
                            "nodeName": "influence",
                            "nodeType": "Bifrost::Nodes::Misc::valueString"
                        },
                        {
                            "nodeName": "influenceChannel",
                            "nodeType": "Bifrost::Nodes::Channel::getChannel"
                        },
                        {
                            "nodeName": "inheritVelocityChannel",
                            "nodeType": "Bifrost::Nodes::Channel::getChannel"
                        },
                        {
                            "nodeName": "inheritVelocity",
                            "nodeType": "Bifrost::Nodes::Misc::valueString"
                        },
                        {
                            "nodeName": "velocity",
                            "nodeType": "Bifrost::Nodes::Misc::valueString"
                        },
                        {
                            "nodeName": "getEmptyVoxelChannelFloat",
                            "nodeType": "Bifrost::Nodes::Empty::voxelChannelFloat"
                        },
                        {
                            "nodeName": "getEmptyVoxelChannelVec3Float",
                            "nodeType": "Bifrost::Nodes::Empty::voxelChannelVec3Float"
                        }
                    ],
                    "connections": [
                        {
                            "source": ".object",
                            "target": "ForceVoxelComponent.object"
                        },
                        {
                            "source": ".velocity",
                            "target": "applyAccelerationForces.velocity"
                        },
                        {
                            "source": ".position",
                            "target": "applyAccelerationForces.position"
                        },
                        {
                            "source": ".dt",
                            "target": "applyAccelerationForces.dt"
                        },
                        {
                            "source": "applyAccelerationForces.outVelocity",
                            "target": ".outVelocity"
                        },
                        {
                            "source": ".object",
                            "target": "forceVoxelComponentName.object"
                        },
                        {
                            "source": "forceVoxelComponentName.value",
                            "target": "ForceVoxelComponent.name"
                        },
                        {
                            "source": "ForceVoxelComponent.value",
                            "target": "boundaryLayerBandwidthChannel.component"
                        },
                        {
                            "source": "ForceVoxelComponent.value",
                            "target": "boundaryLayerStrengthChannel.component"
                        },
                        {
                            "source": "ForceVoxelComponent.value",
                            "target": "directionChannel.component"
                        },
                        {
                            "source": "ForceVoxelComponent.value",
                            "target": "fallOffBandwidthChannel.component"
                        },
                        {
                            "source": "ForceVoxelComponent.value",
                            "target": "forceVoxelVelocityChannel.component"
                        },
                        {
                            "source": "ForceVoxelComponent.value",
                            "target": "influenceChannel.component"
                        },
                        {
                            "source": "ForceVoxelComponent.value",
                            "target": "inheritVelocityChannel.component"
                        },
                        {
                            "source": "forceVoxelVelocityChannel.value",
                            "target": "applyAccelerationForces.velocitySample"
                        },
                        {
                            "source": "fallOffBandwidthChannel.value",
                            "target": "applyAccelerationForces.fallOffBandwidth"
                        },
                        {
                            "source": "influenceChannel.value",
                            "target": "applyAccelerationForces.influence"
                        },
                        {
                            "source": "directionChannel.value",
                            "target": "applyAccelerationForces.directional"
                        },
                        {
                            "source": "inheritVelocityChannel.value",
                            "target": "applyAccelerationForces.inherit"
                        },
                        {
                            "source": "boundaryLayerStrengthChannel.value",
                            "target": "applyAccelerationForces.boundaryLayerStrength"
                        },
                        {
                            "source": "boundaryLayerBandwidthChannel.value",
                            "target": "applyAccelerationForces.boundaryLayerBandwidth"
                        },
                        {
                            "source": "boundaryLayerBandwidth.value",
                            "target": "boundaryLayerBandwidthChannel.name"
                        },
                        {
                            "source": "getEmptyVoxelChannelFloat.value",
                            "target": "boundaryLayerBandwidthChannel.override"
                        },
                        {
                            "source": "boundaryLayerStrength.value",
                            "target": "boundaryLayerStrengthChannel.name"
                        },
                        {
                            "source": "getEmptyVoxelChannelFloat.value",
                            "target": "boundaryLayerStrengthChannel.override"
                        },
                        {
                            "source": "direction.value",
                            "target": "directionChannel.name"
                        },
                        {
                            "source": "getEmptyVoxelChannelVec3Float.value",
                            "target": "directionChannel.override"
                        },
                        {
                            "source": "falloffBandwidth.value",
                            "target": "fallOffBandwidthChannel.name"
                        },
                        {
                            "source": "getEmptyVoxelChannelFloat.value",
                            "target": "fallOffBandwidthChannel.override"
                        },
                        {
                            "source": "velocity.value",
                            "target": "forceVoxelVelocityChannel.name"
                        },
                        {
                            "source": "influence.value",
                            "target": "influenceChannel.name"
                        },
                        {
                            "source": "getEmptyVoxelChannelFloat.value",
                            "target": "influenceChannel.override"
                        },
                        {
                            "source": "inheritVelocity.value",
                            "target": "inheritVelocityChannel.name"
                        },
                        {
                            "source": "getEmptyVoxelChannelFloat.value",
                            "target": "inheritVelocityChannel.override"
                        }
                    ],
                    "values": [
                        {
                            "valueName": "boundaryLayerBandwidth.str",
                            "valueType": "string",
                            "value": "boundaryLayerBandwidth"
                        },
                        {
                            "valueName": "boundaryLayerStrength.str",
                            "valueType": "string",
                            "value": "boundaryLayerStrength"
                        },
                        {
                            "valueName": "direction.str",
                            "valueType": "string",
                            "value": "direction"
                        },
                        {
                            "valueName": "falloffBandwidth.str",
                            "valueType": "string",
                            "value": "falloffBandwidth"
                        },
                        {
                            "valueName": "influence.str",
                            "valueType": "string",
                            "value": "influence"
                        },
                        {
                            "valueName": "inheritVelocity.str",
                            "valueType": "string",
                            "value": "inheritVelocity"
                        },
                        {
                            "valueName": "velocity.str",
                            "valueType": "string",
                            "value": "velocity"
                        }
                    ]
                }
            ],
            "compoundNodes": [
                {
                    "nodeName": "applyVoxelAcceleration",
                    "nodeType": "Bifrost::Nodes::Channel::applyAcceleration"
                },
                {
                    "nodeName": "getVoxelVelocityChannel",
                    "nodeType": "Bifrost::Nodes::Channel::getVoxelChannelVelocity"
                },
                {
                    "nodeName": "getVoxelComponent",
                    "nodeType": "Bifrost::Nodes::Component::getVoxelComponent"
                },
                {
                    "nodeName": "getVelocityName",
                    "nodeType": "Bifrost::Nodes::_privNames::getVelocityName"
                },
                {
                    "nodeName": "getVoxelComponentName",
                    "nodeType": "Bifrost::Nodes::_privNames::getVoxelComponentName"
                },
                {
                    "nodeName": "syncFlow",
                    "nodeType": "Bifrost::Nodes::Object::syncFlow"
                },
                {
                    "nodeName": "getdt",
                    "nodeType": "Bifrost::Nodes::Misc::getDt"
                },
                {
                    "nodeName": "Normalize",
                    "nodeType": "Bifrost::Nodes::Math::normalize"
                },
                {
                    "nodeName": "mul",
                    "nodeType": "Bifrost::Nodes::Math::mul"
                },
                {
                    "nodeName": "syncComponent",
                    "nodeType": "Bifrost::Nodes::Component::syncComponent"
                },
                {
                    "nodeName": "liquidPointPositionChannelName",
                    "nodeType": "Bifrost::Nodes::_privNames::getPointPositionName"
                },
                {
                    "nodeName": "liquidPointComponent",
                    "nodeType": "Bifrost::Nodes::Component::getPointComponent"
                },
                {
                    "nodeName": "liquidPointComponentName",
                    "nodeType": "Bifrost::Nodes::_privNames::getPointComponentName"
                },
                {
                    "nodeName": "liquidPointPositionChannel",
                    "nodeType": "Bifrost::Nodes::Channel::getChannel"
                },
                {
                    "nodeName": "applyPointAcceleration",
                    "nodeType": "Bifrost::Nodes::Channel::applyAcceleration"
                },
                {
                    "nodeName": "LiquidPointVelocityChannelName",
                    "nodeType": "Bifrost::Nodes::_privNames::getPointVelocityName"
                },
                {
                    "nodeName": "VelocityPointChannel",
                    "nodeType": "Bifrost::Nodes::Channel::getChannel"
                },
                {
                    "nodeName": "if",
                    "nodeType": "Bifrost::if"
                },
                {
                    "nodeName": "applyDropletAcceleration",
                    "nodeType": "Bifrost::Nodes::Channel::applyDropletAcceleration"
                },
                {
                    "nodeName": "syncComponent1",
                    "nodeType": "Bifrost::Nodes::Component::syncComponent"
                },
                {
                    "nodeName": "syncObject1",
                    "nodeType": "Bifrost::Nodes::Object::syncFlow"
                },
                {
                    "nodeName": "deleteAndSyncObject",
                    "nodeType": "Bifrost::Nodes::Object::deleteAndSyncObject"
                },
                {
                    "nodeName": "getDropletName",
                    "nodeType": "Bifrost::Nodes::_privNames::getDropletName"
                },
                {
                    "nodeName": "getFloatPointChannel",
                    "nodeType": "Bifrost::Nodes::Channel::getChannel"
                },
                {
                    "nodeName": "applyForcesInternal",
                    "nodeType": "applyForcesInternal"
                },
                {
                    "nodeName": "getEmptyPointChannelVec3Float",
                    "nodeType": "Bifrost::Nodes::Empty::pointChannelVec3Float"
                },
                {
                    "nodeName": "getEmptyPointChannelFloat",
                    "nodeType": "Bifrost::Nodes::Empty::pointChannelFloat"
                }
            ],
            "connections": [
                {
                    "source": ".object",
                    "target": "getVoxelComponentName.object"
                },
                {
                    "source": ".object",
                    "target": "getVoxelComponent.object"
                },
                {
                    "source": ".object",
                    "target": "syncFlow.object"
                },
                {
                    "source": ".gravityVector",
                    "target": "Normalize.vector"
                },
                {
                    "source": ".gravityMagnitude",
                    "target": "mul.second"
                },
                {
                    "source": ".object",
                    "target": "liquidPointComponentName.object"
                },
                {
                    "source": ".object",
                    "target": "liquidPointComponent.object"
                },
                {
                    "source": ".isAdaptive",
                    "target": "if.condition"
                },
                {
                    "source": ".dropletThreshold",
                    "target": "applyDropletAcceleration.dropletThreshold"
                },
                {
                    "source": ".forceObject",
                    "target": "deleteAndSyncObject.objectToDelete"
                },
                {
                    "source": "deleteAndSyncObject.value",
                    "target": ".value"
                },
                {
                    "source": ".forceObject",
                    "target": "applyForcesInternal.object"
                },
                {
                    "source": "getdt.value",
                    "target": "applyVoxelAcceleration.dt"
                },
                {
                    "source": "mul.value",
                    "target": "applyVoxelAcceleration.acceleration"
                },
                {
                    "source": "applyVoxelAcceleration.value",
                    "target": "syncComponent.channel"
                },
                {
                    "source": "applyForcesInternal.outVelocity",
                    "target": "applyVoxelAcceleration.velocityChannel"
                },
                {
                    "source": "getVelocityName.value",
                    "target": "getVoxelVelocityChannel.name"
                },
                {
                    "source": "getVoxelComponent.value",
                    "target": "getVoxelVelocityChannel.component"
                },
                {
                    "source": "getVoxelVelocityChannel.value",
                    "target": "applyForcesInternal.velocity"
                },
                {
                    "source": "getVoxelComponentName.value",
                    "target": "getVoxelComponent.name"
                },
                {
                    "source": "getVoxelComponent.value",
                    "target": "getVelocityName.component"
                },
                {
                    "source": "getVoxelComponent.value",
                    "target": "syncComponent.component"
                },
                {
                    "source": "syncComponent.outputComponent",
                    "target": "syncFlow.item"
                },
                {
                    "source": "syncFlow.value",
                    "target": "syncObject1.object"
                },
                {
                    "source": "getdt.value",
                    "target": "applyPointAcceleration.dt"
                },
                {
                    "source": "getdt.value",
                    "target": "applyDropletAcceleration.dt"
                },
                {
                    "source": "getdt.value",
                    "target": "applyForcesInternal.dt"
                },
                {
                    "source": "Normalize.value",
                    "target": "mul.first"
                },
                {
                    "source": "mul.value",
                    "target": "applyPointAcceleration.acceleration"
                },
                {
                    "source": "mul.value",
                    "target": "applyDropletAcceleration.acceleration"
                },
                {
                    "source": "liquidPointComponent.value",
                    "target": "liquidPointPositionChannelName.component"
                },
                {
                    "source": "liquidPointPositionChannelName.value",
                    "target": "liquidPointPositionChannel.name"
                },
                {
                    "source": "liquidPointComponentName.value",
                    "target": "liquidPointComponent.name"
                },
                {
                    "source": "liquidPointComponent.value",
                    "target": "liquidPointPositionChannel.component"
                },
                {
                    "source": "liquidPointComponent.value",
                    "target": "LiquidPointVelocityChannelName.component"
                },
                {
                    "source": "liquidPointComponent.value",
                    "target": "VelocityPointChannel.component"
                },
                {
                    "source": "liquidPointComponent.value",
                    "target": "syncComponent1.component"
                },
                {
                    "source": "liquidPointComponent.value",
                    "target": "getDropletName.component"
                },
                {
                    "source": "liquidPointComponent.value",
                    "target": "getFloatPointChannel.component"
                },
                {
                    "source": "liquidPointPositionChannel.value",
                    "target": "applyForcesInternal.position"
                },
                {
                    "source": "getEmptyPointChannelVec3Float.value",
                    "target": "liquidPointPositionChannel.override"
                },
                {
                    "source": "VelocityPointChannel.value",
                    "target": "applyPointAcceleration.velocityChannel"
                },
                {
                    "source": "applyPointAcceleration.value",
                    "target": "if.falseCase"
                },
                {
                    "source": "LiquidPointVelocityChannelName.value",
                    "target": "VelocityPointChannel.name"
                },
                {
                    "source": "VelocityPointChannel.value",
                    "target": "applyDropletAcceleration.velocityChannel"
                },
                {
                    "source": "getEmptyPointChannelVec3Float.value",
                    "target": "VelocityPointChannel.override"
                },
                {
                    "source": "applyDropletAcceleration.value",
                    "target": "if.trueCase"
                },
                {
                    "source": "if.output",
                    "target": "syncComponent1.channel"
                },
                {
                    "source": "getFloatPointChannel.value",
                    "target": "applyDropletAcceleration.dropletChannel"
                },
                {
                    "source": "syncComponent1.outputComponent",
                    "target": "syncObject1.item"
                },
                {
                    "source": "syncObject1.value",
                    "target": "deleteAndSyncObject.syncObject"
                },
                {
                    "source": "getDropletName.value",
                    "target": "getFloatPointChannel.name"
                },
                {
                    "source": "getEmptyPointChannelFloat.value",
                    "target": "getFloatPointChannel.override"
                }
            ],
            "values": []
        }
    ]
}